{
    "artifact_sets": [
        {
            "groups": [
                {
                    "items": [
                        {
                            "name": "noblesse-oblige",
                            "pieces": 4
                        }
                    ]
                }
            ]
        },
        {
            "groups": [
                {
                    "items": [
                        {
                            "name": "scroll-of-the-hero-of-cinder-city",
                            "pieces": 4
                        }
                    ]
                }
            ]
        },
        {
            "groups": [
                {
                    "choose": true,
                    "items": [
                        {
                            "name": "hp-set",
                            "pieces": 2
                        },
                        {
                            "name": "er-set",
                            "pieces": 2
                        },
                        {
                            "name": "hp-set",
                            "pieces": 2
                        }
                    ]
                }
            ]
        },
        {
            "groups": [
                {
                    "items": [
                        {
                            "name": "instructor",
                            "pieces": 4,
                            "note": {
                                "en": "This set ideally works best in **heavily reaction-focused** teams like **Hu Tao [[element:vaporize]]** where the **[[stat:em]]** is utilized well. This comes at the cost of making [[character:thoma]] **even more difficult to build**, since you have **fewer potential substat rolls using 4-star artifacts**, and therefore less of a chance of hitting his [[stat:er]] and [[stat:hp]] goals.",
                                "fr": "Ce set fonctionne idéalement dans les équipes fortement axées sur les réactions, comme **Hu Tao [[element:vaporize]]** où la **[[stat:em]]** est bien utilisée. Cela rend cependant le build de [[character:thoma]] **encore plus compliqué**, puisque vous avez **moins de possibilités de substats favorables en utilisant des artefacts 4 étoiles**, et donc moins de chances d'atteindre ses besoins en [[stat:er]] et [[stat:hp]].",
                                "it": "Questo set funziona al meglio **in team che si concentrano fortemente sulle reazioni**, come **Hu Tao [[element:vaporize]]**, dove la **[[stat:em]]** è ben utilizzata. Questo però ha lo svantaggio di rendere la build di [[character:thoma]] **ancora più difficile da realizzare**, dal momento che **i manufatti 4 stelle hanno una quantità minore di statistiche**, e rendono dunque più difficoltoso raggiungere gli obiettivi di [[stat:er]] e di [[stat:hp]].",
                                "ru": "Отлично подходит для отрядов, играющих через реакции, - к примеру, Ху Тао через пар, - где Мастерство стихий довольно полезно. Но Тому в этот сет собрать может быть сложно, так как меньше шансов набрать необходимый уровень ВЭ% и НР%."
                            }
                        }
                    ]
                }
            ]
        },
        {
            "groups": [
                {
                    "items": [
                        {
                            "name": "deepwood-memories",
                            "pieces": 4,
                            "note": {
                                "en": "This set is a support option in teams with a relevant amount of [[element:dendro]] damage, such as [[character:kinich]].",
                                "fr": "Ce set est une option de soutien dans les équipes avec une quantité pertinente de dégâts [[element:dendro]], comme [[character:kinich]].",
                                "it": "Questo set è un'opzione di supporto in team con una quantità rilevante di danni [[element:dendro]] (es. [[character:kinich]]).",
                                "ru": "Вариант в отрядах, играющих от Дендро урона (к примеру, отрядов с Киничем)"
                            }
                        }
                    ]
                }
            ]
        }
    ]
}
