{
    "main_stats": {
        "sands": [
            {
                "name": "em",
                "note": {
                    "en": "Can be preferred for the Sands if [[character:diluc]] is used in a [[element:vaporize]] or [[element:melt]] team.",
                    "fr": "Peut être préféré pour le sablier si [[character:diluc]] est joué dans une équipe [[element:vaporize]] ou [[element:melt]].",
                    "it": "Può essere preferibile se [[character:diluc]] è utilizzato in team **[[element:vaporize]]** o **[[element:melt]]**.",
                    "ru": "Если [[character:diluc]] играет в отряде через [[element:vaporize]]/[[element:melt]], пески на МС предпочтительны."
                }
            },
            "atk%"
        ],
        "goblet": [
            "pyro-dmg"
        ],
        "circlet": [
            "cr/cd"
        ]
    }
}
